<w>
	<team1_icon x="280" y="0" width="175" height="32"><!--
		<texture>ui_inGame2_Mp_HUD_left_panel</texture>
        <text align="c" vert_align="c" font="graffiti32" r="0" g="255" b="0">ui_st_team1_name</text>-->
	</team1_icon>
	<team2_icon x="569" y="0" width="175" height="32"><!--
		<texture>ui_inGame2_Mp_HUD_right_panel</texture>
        <text x="16" align="c" vert_align="c" font="graffiti32" r="0" g="0" b="255">ui_st_team2_name</text>-->
	</team2_icon>
	<team3_icon x="570" y="0" width="140" height="32" stretch="1"><!--
		<texture>ui_inGame2_Mp_HUD_right_panel</texture>
        <text x="16" align="c" vert_align="c" font="graffiti32" r="255" g="180" b="0">ui_st_team3_name</text>-->
	</team3_icon>
	<team4_icon x="600" y="0" width="140" height="32" stretch="1"><!--
		<texture>ui_inGame2_Mp_HUD_right_panel</texture>
        <text x="16" align="c" vert_align="c" font="graffiti32" r="0" g="0" b="0">ui_st_team4_name</text>-->
	</team4_icon>	
	<team5_icon x="630" y="0" width="140" height="32" stretch="1"><!--
		<texture>ui_inGame2_Mp_HUD_left_panel</texture>
        <text align="c" vert_align="c" font="graffiti32" r="0" g="194" b="240">ui_st_team5_name</text>-->
	</team5_icon>	
	<team6_icon x="660" y="0" width="140" height="32" stretch="1"><!--
		<texture>ui_inGame2_Mp_HUD_left_panel</texture>
        <text align="c" vert_align="c" font="graffiti32" r="165" g="40" b="40">ui_st_team6_name</text>-->
	</team6_icon>	
	<team7_icon x="690" y="0" width="140" height="32" stretch="1"><!--
		<texture>ui_inGame2_Mp_HUD_left_panel</texture>
        <text align="c" vert_align="c" font="graffiti32" r="98" g="78" b="24">ui_st_team7_name</text>-->
	</team7_icon>	
	<team8_icon x="720" y="0" width="140" height="32" stretch="1"><!--
		<texture>ui_inGame2_Mp_HUD_left_panel</texture>
        <text align="c" vert_align="c" font="graffiti32" r="120" g="155" b="255">ui_st_team8_name</text>-->
	</team8_icon>		
	<team9_icon x="750" y="0" width="140" height="32" stretch="1"><!--
		<texture>ui_inGame2_Mp_HUD_left_panel</texture>
        <text align="c" vert_align="c" font="graffiti32" r="0" g="95" b="0">ui_st_team9_name</text>-->
	</team9_icon>	

	<team1_score x="470" y="0" width="84" height="41">
		<text align="l" vert_align="c" font="graffiti32" r="0" g="255" b="0"/>
	</team1_score>
	<team2_score x="470" y="0" width="84" height="41">
		<text align="r" vert_align="c" font="graffiti32" r="0" g="0" b="255"/>
	</team2_score>
	<team3_score x="510" y="0" width="67" height="41">
		<text align="r" vert_align="c" font="graffiti32" r="255" g="180" b="0"/>
	</team3_score>
	<team4_score x="550" y="0" width="67" height="41">
		<text align="r" vert_align="c" font="graffiti32" r="0" g="0" b="0"/>
	</team4_score>
	<team5_score x="590" y="0" width="67" height="41">
		<text align="r" vert_align="c" font="graffiti32" r="0" g="195" b="240"/>
	</team5_score>	
	<team6_score x="630" y="0" width="67" height="41">
		<text align="r" vert_align="c" font="graffiti32" r="165" g="40" b="40"/>
	</team6_score>	
	<team7_score x="670" y="0" width="67" height="41">
		<text align="r" vert_align="c" font="graffiti32" r="98" g="78" b="24"/>
	</team7_score>	
	<team8_score x="710" y="0" width="67" height="41">
		<text align="r" vert_align="c" font="graffiti32" r="120" g="155" b="255"/>
	</team8_score>	
	<team9_score x="750" y="0" width="67" height="41">
		<text align="r" vert_align="c" font="graffiti32" r="0" g="95" b="0"/>
	</team9_score>	

	<money_wnd x="878" y="0" width="146" height="160">
		<money_indicator x="0" y="0" width="146" height="42">
			<texture>ui_inGame2_Mp_HUD_money_panel</texture>
			<total_money x="36" y="0" width="103" height="37">
				<text align="c" vert_align="c" font="graffiti32" r="200" g="200" b="200">0</text>
			</total_money>
		</money_indicator>
		<money_change x="36" y="42" width="100" height="30">
			<text font="letterica18" align="c" vert_align="c" r="238" g="155" b="23"></text>
		</money_change>
		<money_bonus_list x="36" y="72" width="100" height="30" always_show_scroll="0">
			<font font="letterica18" align="c" vert_align="c" r="0" g="255" b="0"/>
		</money_bonus_list>
	</money_wnd>

	<rank_wnd x="878" y="0" width="146" height="42">
		<background x="0" y="0" width="60" height="65"/>
		<rank_0 x="5" y="3" width="30" height="31" stretch="1">
			<texture>ui_hud_status_green_01</texture>
		</rank_0>
		<rank_1 x="5" y="3" width="30" height="31" stretch="1">
			<texture>ui_hud_status_green_02</texture>
		</rank_1>
		<rank_2 x="5" y="3" width="30" height="31" stretch="1">
			<texture>ui_hud_status_green_03</texture>
		</rank_2>
		<rank_3 x="5" y="3" width="30" height="31" stretch="1">
			<texture>ui_hud_status_green_04</texture>
		</rank_3>
		<rank_4 x="5" y="3" width="30" height="31" stretch="1">
			<texture>ui_hud_status_green_05</texture>
		</rank_4>
	</rank_wnd>

	<fraglimit x="455" y="0" width="114" height="41">
		<text align="c" vert_align="c" font="letterica16" r="200" g="200" b="200"/>
    </fraglimit>

    <global width="1024" height="768">
	    <auto_static x="455" y="0" width="114" height="41">
		    <texture>ui_inGame2_Mp_HUD_DM</texture>
	    </auto_static>
    </global>
</w>
